aliyunsdkviapi_regen/__init__.py
aliyunsdkviapi_regen/endpoint.py
aliyunsdkviapi_regen/request/__init__.py
aliyunsdkviapi_regen/request/v20211119/CheckDatasetOssBucketCORSRequest.py
aliyunsdkviapi_regen/request/v20211119/CreateDatasetRequest.py
aliyunsdkviapi_regen/request/v20211119/CreateLabelsetRequest.py
aliyunsdkviapi_regen/request/v20211119/CreateServiceRequest.py
aliyunsdkviapi_regen/request/v20211119/CreateTagTaskRequest.py
aliyunsdkviapi_regen/request/v20211119/CreateTrainTaskRequest.py
aliyunsdkviapi_regen/request/v20211119/CreateWorkspaceRequest.py
aliyunsdkviapi_regen/request/v20211119/CustomizeClassifyImageRequest.py
aliyunsdkviapi_regen/request/v20211119/CustomizeDetectImageRequest.py
aliyunsdkviapi_regen/request/v20211119/CustomizeInstanceSegmentImageRequest.py
aliyunsdkviapi_regen/request/v20211119/DebugServiceRequest.py
aliyunsdkviapi_regen/request/v20211119/DeleteDataReflowDataRequest.py
aliyunsdkviapi_regen/request/v20211119/DeleteDatasetRequest.py
aliyunsdkviapi_regen/request/v20211119/DeleteLabelsetDataRequest.py
aliyunsdkviapi_regen/request/v20211119/DeleteLabelsetRequest.py
aliyunsdkviapi_regen/request/v20211119/DeleteServiceRequest.py
aliyunsdkviapi_regen/request/v20211119/DeleteTrainTaskRequest.py
aliyunsdkviapi_regen/request/v20211119/DeleteWorkspaceRequest.py
aliyunsdkviapi_regen/request/v20211119/DisableDataReflowRequest.py
aliyunsdkviapi_regen/request/v20211119/DownloadDatasetRequest.py
aliyunsdkviapi_regen/request/v20211119/DownloadFileNameListRequest.py
aliyunsdkviapi_regen/request/v20211119/DownloadLabelFileRequest.py
aliyunsdkviapi_regen/request/v20211119/EnableDataReflowRequest.py
aliyunsdkviapi_regen/request/v20211119/ExportDataReflowDataListRequest.py
aliyunsdkviapi_regen/request/v20211119/GetDatasetRequest.py
aliyunsdkviapi_regen/request/v20211119/GetDiffCountLabelsetAndDatasetRequest.py
aliyunsdkviapi_regen/request/v20211119/GetLabelDetailRequest.py
aliyunsdkviapi_regen/request/v20211119/GetLabelsetRequest.py
aliyun_python_sdk_viapi_regen-1.0.4.dist-info/LICENSE
aliyun_python_sdk_viapi_regen-1.0.4.dist-info/METADATA
aliyun_python_sdk_viapi_regen-1.0.4.dist-info/WHEEL
aliyun_python_sdk_viapi_regen-1.0.4.dist-info/top_level.txt
aliyun_python_sdk_viapi_regen-1.0.4.dist-info/RECORD
